.coveragerc
CHANGES.rst
CONTRIBUTORS.rst
MANIFEST.in
README.rst
bootstrap-buildout.py
buildout.cfg
setup.py
travis.cfg
docs/LICENSE.GPL
docs/LICENSE.rst
docs/index.rst
src/cciaapd/__init__.py
src/cciaapd.contenttypes.egg-info/PKG-INFO
src/cciaapd.contenttypes.egg-info/SOURCES.txt
src/cciaapd.contenttypes.egg-info/dependency_links.txt
src/cciaapd.contenttypes.egg-info/entry_points.txt
src/cciaapd.contenttypes.egg-info/namespace_packages.txt
src/cciaapd.contenttypes.egg-info/not-zip-safe
src/cciaapd.contenttypes.egg-info/requires.txt
src/cciaapd.contenttypes.egg-info/top_level.txt
src/cciaapd/contenttypes/__init__.py
src/cciaapd/contenttypes/configure.zcml
src/cciaapd/contenttypes/content.py
src/cciaapd/contenttypes/indexers.py
src/cciaapd/contenttypes/interfaces.py
src/cciaapd/contenttypes/permissions.zcml
src/cciaapd/contenttypes/setuphandlers.py
src/cciaapd/contenttypes/testing.py
src/cciaapd/contenttypes/adapters/__init__.py
src/cciaapd/contenttypes/adapters/configure.zcml
src/cciaapd/contenttypes/adapters/extender.py
src/cciaapd/contenttypes/behaviors/__init__.py
src/cciaapd/contenttypes/behaviors/configure.zcml
src/cciaapd/contenttypes/behaviors/related_office.py
src/cciaapd/contenttypes/browser/__init__.py
src/cciaapd/contenttypes/browser/archivio_view.py
src/cciaapd/contenttypes/browser/configure.zcml
src/cciaapd/contenttypes/browser/custom_breadcrumbs_view.py
src/cciaapd/contenttypes/browser/scheda_view.py
src/cciaapd/contenttypes/browser/schede_content_view.py
src/cciaapd/contenttypes/browser/ufficio_form.py
src/cciaapd/contenttypes/browser/ufficio_helper_view.py
src/cciaapd/contenttypes/browser/ufficio_view.py
src/cciaapd/contenttypes/browser/overrides/.gitkeep
src/cciaapd/contenttypes/browser/static/.gitkeep
src/cciaapd/contenttypes/browser/static/archivio.png
src/cciaapd/contenttypes/browser/static/moduli_folder.ico
src/cciaapd/contenttypes/browser/static/riferimenti_folder.ico
src/cciaapd/contenttypes/browser/static/scheda.png
src/cciaapd/contenttypes/browser/static/ufficio.png
src/cciaapd/contenttypes/browser/templates/archivio_view.pt
src/cciaapd/contenttypes/browser/templates/scheda.pt
src/cciaapd/contenttypes/browser/templates/ufficio.pt
src/cciaapd/contenttypes/events/__init__.py
src/cciaapd/contenttypes/events/events_state.py
src/cciaapd/contenttypes/locales/cciaapd.contenttypes.pot
src/cciaapd/contenttypes/locales/update.sh
